setup.py
DoThings.egg-info/PKG-INFO
DoThings.egg-info/SOURCES.txt
DoThings.egg-info/dependency_links.txt
DoThings.egg-info/entry_points.txt
DoThings.egg-info/requires.txt
DoThings.egg-info/top_level.txt
things/__init__.py
things/things.py