Metadata-Version: 1.0
Name: DoThings
Version: 0.2
Summary: Simple To-Do-List in Termial
Home-page: https://github.com/marzinz/things/
Author: Marzin Zhu
Author-email: marzin.zhu@gmail.com
License: BSD
Platform: UNKNOWN
